{
  "_meta": {
    "release": "0.9.6",
    "target": "ur",
    "creator": "techninja via GoogleTranslate"
  },
  "info": {
    "description": "پینٹنگ موڈ: اپنے ڈرائنگ پرنٹ!",
    "title": "خود کار طریقے سے پینٹ",
    "detail": "خود کار طریقے سے ایک دیئے گئے اچھی طرح سے قائم SVG فائل پینٹ.",
    "word": "پرنٹ"
  },
  "control": {
    "title": "آٹو پینٹ",
    "subtitle": "کنٹرول"
  },
  "status": {
    "initial": "آپ کی تصویر پینٹنگ شروع کرنے کے لئے کلک کریں!",
    "park": "گھر کی پوزیشن پر واپس گاڑی میں منتقل کریں",
    "ready": "آپ کی تصویر پینٹنگ شروع کرنے کے لئے کلک کریں!",
    "pause": "لمحے بھر کے موجودہ آپریشن کو روکنے کے",
    "resume": "آپریشن دوبارہ شروع کے لئے کلک کریں",
    "confirm": "آپ کو موجودہ پرنٹ کام کو منسوخ اور (مثال کے طور پر، ایک نیا پرنٹ کام شروع کرنے کے لئے) ری سیٹ کرنا چاہتے ہیں اس بات کا یقین کر رہے ہیں؟",
    "cancelled": "کینوس ری سیٹ، چرخی اور پرنٹنگ منسوخ."
  }
}
